LICENSE
blacksheep_rich_log/__init__.py
blacksheep_rich_log/py.typed
blacksheep_rich_log-0.0.2.dist-info/LICENSE
blacksheep_rich_log-0.0.2.dist-info/METADATA
blacksheep_rich_log-0.0.2.dist-info/WHEEL
blacksheep_rich_log-0.0.2.dist-info/RECORD
